[
  { "id": "log-01", "userId": "user-01", "userName": "Nguyễn Thị Minh Châu", "action": "đăng nhập", "target": "Hệ thống", "timestamp": "2024-03-17T08:05:00" },
  { "id": "log-02", "userId": "user-02", "userName": "Trần Đức Mạnh", "action": "đăng ký khóa học", "target": "Quản lý Di sản Văn hóa Phi vật thể", "timestamp": "2024-03-17T08:12:00" },
  { "id": "log-03", "userId": "user-03", "userName": "Lê Thị Phương Thảo", "action": "hoàn thành bài kiểm tra", "target": "Kỹ năng Hướng dẫn Du lịch", "timestamp": "2024-03-17T08:30:00" },
  { "id": "log-04", "userId": "user-04", "userName": "Phạm Văn Hải", "action": "cập nhật hồ sơ", "target": "Hồ sơ cá nhân", "timestamp": "2024-03-17T08:45:00" },
  { "id": "log-05", "userId": "user-05", "userName": "Hoàng Thị Lan", "action": "đăng nhập", "target": "Hệ thống", "timestamp": "2024-03-17T09:00:00" },
  { "id": "log-06", "userId": "user-06", "userName": "PGS.TS Nguyễn Văn An", "action": "tạo khóa học", "target": "Di sản Văn hóa Thế giới tại Việt Nam", "timestamp": "2024-03-17T09:10:00" },
  { "id": "log-07", "userId": "user-01", "userName": "Nguyễn Thị Minh Châu", "action": "xem bài giảng", "target": "Bảo tồn Di tích Lịch sử", "timestamp": "2024-03-17T09:20:00" },
  { "id": "log-08", "userId": "user-07", "userName": "TS. Trần Thị Bích Ngọc", "action": "xuất báo cáo", "target": "Báo cáo tháng 3/2024", "timestamp": "2024-03-17T09:35:00" },
  { "id": "log-09", "userId": "user-02", "userName": "Trần Đức Mạnh", "action": "hoàn thành khóa học", "target": "Nghiệp vụ Hướng dẫn Du lịch", "timestamp": "2024-03-17T09:50:00" },
  { "id": "log-10", "userId": "user-08", "userName": "ThS. Lê Minh Phương", "action": "tải lên tài liệu", "target": "Phát triển Du lịch Bền vững", "timestamp": "2024-03-17T10:00:00" },
  { "id": "log-11", "userId": "user-03", "userName": "Lê Thị Phương Thảo", "action": "đăng ký khóa học", "target": "Yoga và Thiền định cho Người mới", "timestamp": "2024-03-17T10:15:00" },
  { "id": "log-12", "userId": "user-09", "userName": "Đinh Thị Thu Hương", "action": "phê duyệt khóa học", "target": "Võ thuật cổ truyền Việt Nam", "timestamp": "2024-03-17T10:30:00" },
  { "id": "log-13", "userId": "user-04", "userName": "Phạm Văn Hải", "action": "đăng nhập", "target": "Hệ thống", "timestamp": "2024-03-17T10:45:00" },
  { "id": "log-14", "userId": "user-05", "userName": "Hoàng Thị Lan", "action": "hoàn thành bài kiểm tra", "target": "Quản lý Sự kiện Văn hóa", "timestamp": "2024-03-17T11:00:00" },
  { "id": "log-15", "userId": "user-10", "userName": "Vũ Quang Minh", "action": "vô hiệu hóa tài khoản", "target": "Người dùng user-15", "timestamp": "2024-03-17T11:15:00" },
  { "id": "log-16", "userId": "user-01", "userName": "Nguyễn Thị Minh Châu", "action": "tải chứng chỉ", "target": "Chứng chỉ Hoàn thành Khóa học", "timestamp": "2024-03-17T11:30:00" },
  { "id": "log-17", "userId": "user-06", "userName": "PGS.TS Nguyễn Văn An", "action": "chỉnh sửa khóa học", "target": "Quản lý Di sản Văn hóa Phi vật thể", "timestamp": "2024-03-17T11:45:00" },
  { "id": "log-18", "userId": "user-02", "userName": "Trần Đức Mạnh", "action": "đăng nhập", "target": "Hệ thống", "timestamp": "2024-03-17T12:00:00" },
  { "id": "log-19", "userId": "user-03", "userName": "Lê Thị Phương Thảo", "action": "xem bài giảng", "target": "Tổ chức Sự kiện Thể thao Quần chúng", "timestamp": "2024-03-17T12:30:00" },
  { "id": "log-20", "userId": "user-09", "userName": "Đinh Thị Thu Hương", "action": "cập nhật cài đặt", "target": "Cài đặt hệ thống", "timestamp": "2024-03-17T13:00:00" },
  { "id": "log-21", "userId": "user-07", "userName": "TS. Trần Thị Bích Ngọc", "action": "tạo bài kiểm tra", "target": "Kiểm tra cuối khóa Du lịch", "timestamp": "2024-03-17T13:30:00" },
  { "id": "log-22", "userId": "user-04", "userName": "Phạm Văn Hải", "action": "đăng ký khóa học", "target": "Bơi lội Cơ bản", "timestamp": "2024-03-17T14:00:00" },
  { "id": "log-23", "userId": "user-05", "userName": "Hoàng Thị Lan", "action": "đăng nhập", "target": "Hệ thống", "timestamp": "2024-03-17T14:15:00" },
  { "id": "log-24", "userId": "user-08", "userName": "ThS. Lê Minh Phương", "action": "đăng xuất", "target": "Hệ thống", "timestamp": "2024-03-17T14:30:00" },
  { "id": "log-25", "userId": "user-10", "userName": "Vũ Quang Minh", "action": "thêm người dùng", "target": "Nguyễn Văn Bình", "timestamp": "2024-03-17T15:00:00" },
  { "id": "log-26", "userId": "user-01", "userName": "Nguyễn Thị Minh Châu", "action": "hoàn thành bài kiểm tra", "target": "Di sản Văn hóa Thế giới", "timestamp": "2024-03-17T15:20:00" },
  { "id": "log-27", "userId": "user-06", "userName": "PGS.TS Nguyễn Văn An", "action": "xuất báo cáo", "target": "Báo cáo hiệu quả giảng dạy", "timestamp": "2024-03-17T15:45:00" },
  { "id": "log-28", "userId": "user-02", "userName": "Trần Đức Mạnh", "action": "cập nhật hồ sơ", "target": "Hồ sơ cá nhân", "timestamp": "2024-03-17T16:00:00" },
  { "id": "log-29", "userId": "user-09", "userName": "Đinh Thị Thu Hương", "action": "từ chối khóa học", "target": "Khóa học thử nghiệm", "timestamp": "2024-03-17T16:30:00" },
  { "id": "log-30", "userId": "user-03", "userName": "Lê Thị Phương Thảo", "action": "đăng xuất", "target": "Hệ thống", "timestamp": "2024-03-17T17:00:00" }
]
